difPy/__init__.py
difPy/dif.py
difPy/difPy.bat
difPy/difTester.py
difPy/version.py
difPy-4.1.2.dist-info/LICENSE.txt
difPy-4.1.2.dist-info/METADATA
difPy-4.1.2.dist-info/WHEEL
difPy-4.1.2.dist-info/top_level.txt
difPy-4.1.2.dist-info/RECORD
