Metadata-Version: 2.1
Name: difPy
Version: 4.1.2
Summary: difPy Duplicate Image Finder - automated search for duplicate or similar images.
Home-page: https://github.com/elisemercury/Duplicate-Image-Finder
Download-URL: https://github.com/elisemercury/Duplicate-Image-Finder/archive/refs/tags/v4.1.2.tar.gz
Author: Elise Landman
Author-email: elisejlandman@hotmail.com
License: MIT
Keywords: duplicate,image,finder,similarity,pictures
Classifier: Development Status :: 5 - Production/Stable
Classifier: Intended Audience :: Developers
Classifier: Topic :: Software Development :: Build Tools
Classifier: License :: OSI Approved :: MIT License
Classifier: Programming Language :: Python
Classifier: Programming Language :: Python :: 3.11
Requires-Python: >=3.8
License-File: LICENSE.txt
Requires-Dist: numpy >=1.24.2
Requires-Dist: Pillow >=9.4.0
